tokensynth-0.0.4.dist-info/METADATA
tokensynth-0.0.4.dist-info/WHEEL
tokensynth-0.0.4.dist-info/entry_points.txt
tokensynth-0.0.4.dist-info/licenses/LICENSE
tokensynth/__init__.py
tokensynth/clap.py
tokensynth/dac_decoder.py
tokensynth/model.py
tokensynth/utils.py
tokensynth-0.0.4.dist-info/RECORD
