Metadata-Version: 2.1
Name: tokensynth
Version: 0.0.4
Summary: tokensynth
Author-Email: Kyungsu Kim <kyungsu.kim@snu.ac.kr>
License: MIT
Project-URL: Repository, https://github.com/KyungsuKim42/tokensynth
Requires-Python: >=3.10
Requires-Dist: audiofile
Requires-Dist: appdirs
Requires-Dist: descript-audio-codec
Requires-Dist: huggingface-hub
Requires-Dist: laion-clap==1.1.6
Requires-Dist: librosa
Requires-Dist: numpy
Requires-Dist: pretty-midi
Requires-Dist: pytest
Requires-Dist: setuptools
Requires-Dist: torch<2.6.0,>=2.0.0
Requires-Dist: torchaudio>=2.0.0
Requires-Dist: torchvision>=0.15.0
Requires-Dist: tqdm
Requires-Dist: transformers
